atform/__init__.py
atform/addtest.py
atform/arg.py
atform/cache.py
atform/error.py
atform/field.py
atform/format.py
atform/gen.py
atform/id.py
atform/idlock.py
atform/image.py
atform/label.py
atform/meta.py
atform/misc.py
atform/parallelbuild.py
atform/procedure.py
atform/ref.py
atform/sig.py
atform/state.py
atform/vcs.py
atform/version.py
atform/gui/__init__.py
atform/gui/app.py
atform/gui/build.py
atform/gui/buildlist.py
atform/gui/common.py
atform/gui/diff.py
atform/gui/diffwidget.py
atform/gui/preview.py
atform/gui/search.py
atform/gui/searchwidget.py
atform/gui/selectlist.py
atform/gui/selectref.py
atform/gui/statusbar.py
atform/gui/testlist.py
atform/gui/tkwidget.py
atform/pdf/__init__.py
atform/pdf/acroform.py
atform/pdf/approval.py
atform/pdf/doc.py
atform/pdf/environ.py
atform/pdf/equip.py
atform/pdf/layout.py
atform/pdf/notes.py
atform/pdf/objective.py
atform/pdf/paragraph.py
atform/pdf/precondition.py
atform/pdf/procedure.py
atform/pdf/refs.py
atform/pdf/section.py
atform/pdf/textstyle.py
atform/pdf/title.py
atform-1.0.dist-info/METADATA
atform-1.0.dist-info/WHEEL
atform-1.0.dist-info/licenses/LICENSE.txt
atform-1.0.dist-info/RECORD
