Metadata-Version: 2.4
Name: atform
Version: 1.0
Summary: Acceptance test procedure form generator.
Project-URL: Homepage, https://github.com/jvalenzuela/atform
Project-URL: Repository, https://github.com/jvalenzuela/atform.git
Project-URL: Issues, https://github.com/jvalenzuela/atform/issues
Author: Jason Valenzuela
Author-email: jvalenzuela1977@gmail.com
License: BSD 3-Clause License
License-File: LICENSE.txt
Classifier: Environment :: Console
Classifier: License :: OSI Approved :: BSD License
Classifier: Operating System :: OS Independent
Classifier: Programming Language :: Python :: 3
Classifier: Programming Language :: Python :: 3 :: Only
Classifier: Programming Language :: Python :: 3.9
Classifier: Programming Language :: Python :: 3.10
Classifier: Programming Language :: Python :: 3.11
Classifier: Programming Language :: Python :: 3.12
Classifier: Programming Language :: Python :: 3.13
Classifier: Topic :: Software Development :: Testing :: Acceptance
Classifier: Topic :: Text Processing :: Markup
Requires-Python: <3.14,>=3.9
Requires-Dist: pillow
Requires-Dist: reportlab>=4.2.0
Requires-Dist: whoosh
